pcmiler/__init__.py
tests/__init__.py
tests/test_package.py
pcmiler-0.0.0.dist-info/LICENSE
pcmiler-0.0.0.dist-info/METADATA
pcmiler-0.0.0.dist-info/WHEEL
pcmiler-0.0.0.dist-info/entry_points.txt
pcmiler-0.0.0.dist-info/top_level.txt
pcmiler-0.0.0.dist-info/RECORD
